{
  "cards": [
    {
      "id": 1774149036146,
      "name": "Stellar Crown - Squirtle #148 Slab - PSA 10",
      "set": "",
      "rarity": "Slab - PSA 10",
      "cond": "Slab - PSA 10",
      "qty": 1,
      "cost": 310
    },
    {
      "id": 1774149036147,
      "name": "JP Magikarp Triplet Beat #080 Slab - PSA 10",
      "set": "",
      "rarity": "Slab - PSA 10",
      "cond": "Slab - PSA 10",
      "qty": 1,
      "cost": 178.5
    },
    {
      "id": 1774149036149,
      "name": "Stain Glass Birds #SM210 Slab - PSA 10",
      "set": "",
      "rarity": "Slab - PSA 10",
      "cond": "Slab - PSA 10",
      "qty": 1,
      "cost": 330
    },
    {
      "id": 1774149036150,
      "name": "Mcdonalds Set Raw",
      "set": "",
      "rarity": "Raw",
      "cond": "Raw",
      "qty": 1,
      "cost": 69.98
    },
    {
      "id": 1774149036151,
      "name": "Team Rocket's Meowth 203/182 Sv10: Destined Rivals Holo Raw",
      "set": "",
      "rarity": "Raw",
      "cond": "Raw",
      "qty": 1,
      "cost": 31
    },
    {
      "id": 1774149036152,
      "name": "[NM] Holo Dark Gyarados Celebrations 8/82 Pokemon TCG Raw",
      "set": "",
      "rarity": "Raw",
      "cond": "Raw",
      "qty": 1,
      "cost": 5.5
    },
    {
      "id": 1774149036153,
      "name": "Gengar VMAX 157/264 Ultra Rare Holo NM Pokemon SWSH08: Fusion Strike Raw",
      "set": "",
      "rarity": "Raw",
      "cond": "Raw",
      "qty": 1,
      "cost": 56
    },
    {
      "id": 1774149036154,
      "name": "1999 POKEMON JAPANESE GYM 2 #130 GIOVANNI'S GYARADOS-HOLO PSA 10",
      "set": "",
      "rarity": "Slab - PSA",
      "cond": "Slab - PSA",
      "qty": 1,
      "cost": 360.55
    },
    {
      "id": 1774149036155,
      "name": "CGC 10 Japanese Tangela 178/165 151 2023 AR Pokemon Card TCG",
      "set": "",
      "rarity": "Slab - CGC 10",
      "cond": "Slab - CGC 10",
      "qty": 1,
      "cost": 10
    },
    {
      "id": 1774149036156,
      "name": "2023 POKEMON PALDEA EVOLVED SPECIAL ILLUSTRATION RARE #258 SKELEDIRGE EX PSA 10",
      "set": "",
      "rarity": "Slab - PSA 10",
      "cond": "Slab - PSA 10",
      "qty": 1,
      "cost": 91
    }
  ],
  "sealed": [
    {
      "id": 1774149036157,
      "name": "Mega Latias Ex Box",
      "type": "Box",
      "set": "Mega Evolutions",
      "qty": 6,
      "price": 24.87,
      "date": "2026-03-22",
      "notes": "Walmart"
    },
    {
      "id": 1774149036158,
      "name": "SV10.5 Unova Mini Tin",
      "type": "Tins",
      "set": "BB/WF",
      "qty": 9,
      "price": 12.87,
      "date": "2026-03-22",
      "notes": "Walmart"
    },
    {
      "id": 1774149036159,
      "name": "ME01 Mega Evolutions ETB (Gardivoir)",
      "type": "ETB",
      "set": "Mega Evolutions",
      "qty": 1,
      "price": 49.99,
      "date": "2026-03-22",
      "notes": "Bestbuy MSRP"
    },
    {
      "id": 1774149036162,
      "name": "Prismatic Costco ETB + Booster Bundle 2pk",
      "type": "ETB",
      "set": "Prismatic Evolutions",
      "qty": 1,
      "price": 59.99,
      "date": "2026-03-22",
      "notes": "Costco"
    },
    {
      "id": 1774149036163,
      "name": "Prismatic Costco Tin Set",
      "type": "Tins",
      "set": "Prismatic Evolutions",
      "qty": 2,
      "price": 59.99,
      "date": "2026-03-22",
      "notes": "Costco"
    },
    {
      "id": 1774149036164,
      "name": "Pokemon Fall Team Rockets Tin",
      "type": "Tins",
      "set": "",
      "qty": 2,
      "price": 31.99,
      "date": "2026-03-22",
      "notes": "Walmart"
    },
    {
      "id": 1774149036165,
      "name": "Pokemon Trading Card Games Scarlet & Violet 8 Surging Sparks Booster Bundle",
      "type": "Booster Bundle",
      "set": "Surging Sparks",
      "qty": 2,
      "price": 34.99,
      "date": "2026-03-22",
      "notes": "Walmart"
    },
    {
      "id": 1774149036166,
      "name": "Charizard Phantasmal Flames UPC",
      "type": "UPC",
      "set": "Phantasmal Flames",
      "qty": 14,
      "price": 118.83,
      "date": "2026-03-22",
      "notes": "WMT, Costco etc"
    },
    {
      "id": 1774149036167,
      "name": "Scarlet & Violet Twilight Masquerade Elite Trainer Box",
      "type": "ETB",
      "set": "Twilight Masquerade",
      "qty": 1,
      "price": 59.24,
      "date": "2026-03-22",
      "notes": "Amzn + Danny"
    },
    {
      "id": 1774149036168,
      "name": "ME02 Phantasmal Flames 3 Pack Blister",
      "type": "Blister",
      "set": "Phantasmal Flames",
      "qty": 4,
      "price": 15.87,
      "date": "2026-03-22",
      "notes": "Walmart Pending / 6 to Danny"
    },
    {
      "id": 1774149036169,
      "name": "ME02 Phantasmal Flames Booster Bundle",
      "type": "Booster Bundle",
      "set": "Phantasmal Flames",
      "qty": 5,
      "price": 32.47,
      "date": "2026-03-22",
      "notes": "Walmart"
    },
    {
      "id": 1774149036170,
      "name": "ME01 Mega Evolution Booster Bundle",
      "type": "Booster Bundle",
      "set": "Mega Evolutions",
      "qty": 1,
      "price": 32.5,
      "date": "2026-03-22",
      "notes": "Danny"
    },
    {
      "id": 1774149036171,
      "name": "Scarlet & Violet 10.5 Black Bolt Elite Trainer Box",
      "type": "ETB",
      "set": "Black Bolt",
      "qty": 1,
      "price": 62.25,
      "date": "2026-03-22",
      "notes": "Walmart"
    },
    {
      "id": 1774149036172,
      "name": "Scarlet & Violet 10.5 White Flare Elite Trainer Box",
      "type": "ETB",
      "set": "White Flare",
      "qty": 2,
      "price": 61.13,
      "date": "2026-03-22",
      "notes": "Danny+Walmart"
    },
    {
      "id": 1774149036173,
      "name": "Scarlet & Violet Stellar Crown Pokemon Center ETB",
      "type": "ETB",
      "set": "Stellar Crown",
      "qty": 1,
      "price": 59.99,
      "date": "2026-03-22",
      "notes": "PKC"
    },
    {
      "id": 1774149036174,
      "name": "ME03 Ascended Heroes Elite Trainer Box (PKC)",
      "type": "ETB",
      "set": "Ascended Heroes",
      "qty": 3,
      "price": 59.99,
      "date": "2026-03-22",
      "notes": "PKC - Preorder"
    },
    {
      "id": 1774149036175,
      "name": "ME03 Ascended Heroes Elite Trainer Box",
      "type": "ETB",
      "set": "Ascended Heroes",
      "qty": 1,
      "price": 80.86,
      "date": "2026-03-22",
      "notes": "XPCollect"
    },
    {
      "id": 1774149036176,
      "name": "ME03 Ascended Heroes Booster Bundle (6 Packs)",
      "type": "Booster Bundle",
      "set": "Ascended Heroes",
      "qty": 4,
      "price": 26.94,
      "date": "2026-03-22",
      "notes": "PKC"
    },
    {
      "id": 1774149036177,
      "name": "Mega Evolution Sleeved Booster Pack (10 Cards)",
      "type": "Booster Pack",
      "set": "Mega Evolutions",
      "qty": 11,
      "price": 4.92,
      "date": "2026-03-22",
      "notes": "PKC + bnb"
    },
    {
      "id": 1774149036178,
      "name": "Pokemon Salamence ex & Reshiram ex Premium Collection",
      "type": "Box",
      "set": "",
      "qty": 2,
      "price": 49.99,
      "date": "2026-03-22",
      "notes": "PoketexasTCG"
    },
    {
      "id": 1774149036179,
      "name": "Mega Evolution Booster Box - Enhanced",
      "type": "Booster Box",
      "set": "Mega Evolutions",
      "qty": 3,
      "price": 235.9,
      "date": "2026-03-22",
      "notes": "PoketexasTCG/pfootball"
    },
    {
      "id": 1774149036180,
      "name": "Destined Rivals Booster Box - SV10",
      "type": "Booster Box",
      "set": "Destined Rivals",
      "qty": 2,
      "price": 315,
      "date": "2026-03-22",
      "notes": "FB Mkt"
    },
    {
      "id": 1774149036181,
      "name": "Stellar Crown Booster Box - SV07",
      "type": "Booster Box",
      "set": "Stellar Crown",
      "qty": 1,
      "price": 255,
      "date": "2026-03-22",
      "notes": "Ryan's Cardhouse Ebay"
    },
    {
      "id": 1774149036182,
      "name": "Journey Together Booster Box - SV10",
      "type": "Booster Box",
      "set": "Journey Together",
      "qty": 3,
      "price": 252.26,
      "date": "2026-03-22",
      "notes": "Ryan's Cardhouse Ebay"
    },
    {
      "id": 1774149036183,
      "name": "Surging Sparks Booster Box - SV08",
      "type": "Booster Box",
      "set": "Surging Sparks",
      "qty": 2,
      "price": 225.25,
      "date": "2026-03-22",
      "notes": "Ryan's+Ebay"
    },
    {
      "id": 1774149036184,
      "name": "Phantasmal Flames Booster Box",
      "type": "Booster Box",
      "set": "Phantasmal Flames",
      "qty": 1,
      "price": 227.49,
      "date": "2026-03-22",
      "notes": "pfootball/PoketexasTCG"
    },
    {
      "id": 1774149036185,
      "name": "Twilight Masquerade Booster Box",
      "type": "Booster Box",
      "set": "Twilight Masquerade",
      "qty": 1,
      "price": 318,
      "date": "2026-03-22",
      "notes": "Ryan's Cardhouse Ebay"
    },
    {
      "id": 1774149036186,
      "name": "151 Booster Pack",
      "type": "Booster Pack",
      "set": "151",
      "qty": 4,
      "price": 12.5,
      "date": "2026-03-22",
      "notes": "Stream"
    },
    {
      "id": 1774149036187,
      "name": "Paldean Fates Booster Pack",
      "type": "Booster Pack",
      "set": "Paldean Fates",
      "qty": 2,
      "price": 12.5,
      "date": "2026-03-22",
      "notes": "Stream"
    },
    {
      "id": 1774149036188,
      "name": "Pokemon cards Pack mcdonalds 2021",
      "type": "Sealed",
      "set": "",
      "qty": 3,
      "price": 5,
      "date": "2026-03-22",
      "notes": "Stream"
    },
    {
      "id": 1774149036189,
      "name": "Paldean Fates Booster Bundle (6 Packs)",
      "type": "Booster Bundle",
      "set": "Paldean Fates",
      "qty": 1,
      "price": 76,
      "date": "2026-03-22",
      "notes": "Stream"
    },
    {
      "id": 1774149036190,
      "name": "Pokemon TCG: Tornadus, Thundurus & Landorus Cards with 2 Booster Packs & Coin",
      "type": "Blister Pack",
      "set": "",
      "qty": 2,
      "price": 9.99,
      "date": "2026-03-22",
      "notes": "PKC"
    },
    {
      "id": 1774149036191,
      "name": "Mega Evo Mini Tins (Kangakhn + Venasaur)",
      "type": "Tins",
      "set": "",
      "qty": 5,
      "price": 11.87,
      "date": "2026-03-22",
      "notes": "Walmart"
    },
    {
      "id": 1774149036192,
      "name": "Mega Evo Mini Tins",
      "type": "Tins",
      "set": "",
      "qty": 7,
      "price": 10.93,
      "date": "2026-03-22",
      "notes": "DG + Walmart"
    },
    {
      "id": 1774149036193,
      "name": "Phantasmal Flames ETB",
      "type": "ETB",
      "set": "Phantasmal Flames",
      "qty": 1,
      "price": 79.99,
      "date": "2026-03-22",
      "notes": "PoketexasTCG"
    },
    {
      "id": 1774149036194,
      "name": "Twilight Masquerade ETB Sealed Case (10X) 50% split w/ Danny",
      "type": "ETB",
      "set": "Twilight Masquerade",
      "qty": 0.5,
      "price": 560,
      "date": "2026-03-22",
      "notes": "pfootball"
    },
    {
      "id": 1774149036195,
      "name": "Incineroar ex and Torterra ex Special Collection Box",
      "type": "Box",
      "set": "",
      "qty": 1,
      "price": 25,
      "date": "2026-03-22",
      "notes": "Walmart"
    },
    {
      "id": 1774149036196,
      "name": "Lugia ex & Latias ex Premium Collection",
      "type": "Box",
      "set": "",
      "qty": 1,
      "price": 49.99,
      "date": "2026-03-22",
      "notes": "Target"
    },
    {
      "id": 1774149036197,
      "name": "Archaludon ex & Reshiram ex",
      "type": "Box",
      "set": "",
      "qty": 1,
      "price": 34.99,
      "date": "2026-03-22",
      "notes": "Target"
    },
    {
      "id": 1774149036198,
      "name": "Black Kyurem ex & Melmetal ex",
      "type": "Box",
      "set": "",
      "qty": 1,
      "price": 34.99,
      "date": "2026-03-22",
      "notes": "Target"
    },
    {
      "id": 1774149036199,
      "name": "Paradox Destinies Iron Crown ex Tin",
      "type": "Tins",
      "set": "",
      "qty": 1,
      "price": 17,
      "date": "2026-03-22",
      "notes": "Walmart"
    },
    {
      "id": 1774149036200,
      "name": "Legendary Warriors Premium Collection",
      "type": "Box",
      "set": "",
      "qty": 1,
      "price": 104.99,
      "date": "2026-03-22",
      "notes": "Walmart"
    },
    {
      "id": 1774149036201,
      "name": "Prismatic Poster Collection",
      "type": "Box",
      "set": "Prismatic Evolutions",
      "qty": 2,
      "price": 20,
      "date": "2026-03-22",
      "notes": "pfootball"
    },
    {
      "id": 1774149036202,
      "name": "Great Tusk Iron Threads Ex Premium Collection",
      "type": "Box",
      "set": "",
      "qty": 1,
      "price": 75,
      "date": "2026-03-22",
      "notes": "Walmart"
    },
    {
      "id": 1774149036203,
      "name": "Shrouded Fables Booster Bundle",
      "type": "Booster Bundle",
      "set": "Shrouded Fables",
      "qty": 1,
      "price": 29.26,
      "date": "2026-03-22",
      "notes": "PKC"
    },
    {
      "id": 1774149036204,
      "name": "Prismatic Evolutions Premium Figure Box",
      "type": "Box",
      "set": "Prismatic Evolutions",
      "qty": 2,
      "price": 86.66,
      "date": "2026-03-22",
      "notes": "Macy's/Poketexas"
    },
    {
      "id": 1774149036205,
      "name": "Unova Heavy Hitters Box",
      "type": "Box",
      "set": "",
      "qty": 7,
      "price": 53.89,
      "date": "2026-03-22",
      "notes": "Costco"
    },
    {
      "id": 1774149036206,
      "name": "Phantasmal Flames Booster Box Sealed Case",
      "type": "Booster Box",
      "set": "Phantasmal Flames",
      "qty": 1,
      "price": 1339.16,
      "date": "2026-03-22",
      "notes": "pfootball"
    },
    {
      "id": 1774149036207,
      "name": "Prismatic Evolutions ETB",
      "type": "ETB",
      "set": "Prismatic Evolutions",
      "qty": 2,
      "price": 32.1,
      "date": "2026-03-22",
      "notes": "DG"
    },
    {
      "id": 1774149036208,
      "name": "Prismatic Evolutions Tech Sticker Collection Glaceon",
      "type": "Blister",
      "set": "Prismatic Evolutions",
      "qty": 1,
      "price": 19.64,
      "date": "2026-03-22",
      "notes": "Target"
    },
    {
      "id": 1774149036209,
      "name": "Prismatic Evolutions Tech Sticker Collection Glaceon",
      "type": "Blister",
      "set": "Prismatic Evolutions",
      "qty": 4,
      "price": 16,
      "date": "2026-03-22",
      "notes": "Dollar General"
    },
    {
      "id": 1774149036210,
      "name": "Journey Together Sleeved Booster",
      "type": "Booster",
      "set": "Journey Together",
      "qty": 36,
      "price": 5.44,
      "date": "2026-03-22",
      "notes": "pfootball"
    },
    {
      "id": 1774149036211,
      "name": "Destined Rivals Sleeved Booster",
      "type": "Booster",
      "set": "Destined Rivals",
      "qty": 42,
      "price": 6.31,
      "date": "2026-03-22",
      "notes": "FB marketplace, BB, PKC"
    },
    {
      "id": 1774149036212,
      "name": "Prismatic Booster Bundle",
      "type": "Booster",
      "set": "Prismatic Evolutions",
      "qty": 9,
      "price": 34.9,
      "date": "2026-03-22",
      "notes": "Walmart, Target, PKC"
    },
    {
      "id": 1774149036213,
      "name": "Stacking Tins (3 packs)",
      "type": "Tins",
      "set": "",
      "qty": 7,
      "price": 17.12,
      "date": "2026-03-22",
      "notes": "DG"
    },
    {
      "id": 1774149036214,
      "name": "ME04 Perfect Order ETB (PKC)",
      "type": "ETB",
      "set": "",
      "qty": 2,
      "price": 59.99,
      "date": "2026-03-22",
      "notes": "PKC"
    },
    {
      "id": 1774149036215,
      "name": "ME04 Perfect Order ETB",
      "type": "ETB",
      "set": "",
      "qty": 2,
      "price": 62.66,
      "date": "2026-03-22",
      "notes": "Forge&Fire"
    },
    {
      "id": 1774149036216,
      "name": "ME04 Perfect Order Booster Box",
      "type": "Booster Box",
      "set": "",
      "qty": 2,
      "price": 170.82,
      "date": "2026-03-22",
      "notes": "PKC+Forge Fire"
    },
    {
      "id": 1774149036217,
      "name": "ME04 Perfect Order Booster Bundle",
      "type": "Booster Bundle",
      "set": "",
      "qty": 2,
      "price": 26.94,
      "date": "2026-03-22",
      "notes": "PKC"
    },
    {
      "id": 1774149036218,
      "name": "151 Booster Packs",
      "type": "Booster",
      "set": "151",
      "qty": 36,
      "price": 16.18,
      "date": "2026-03-22",
      "notes": "pfootball"
    },
    {
      "id": 1774149036219,
      "name": "151 Mini Tin Display (10)",
      "type": "Tins",
      "set": "151",
      "qty": 1,
      "price": 354.66,
      "date": "2026-03-22",
      "notes": "Pfootballpete"
    },
    {
      "id": 1774149036220,
      "name": "Charizard Phantasmal Flames UPC",
      "type": "UPC",
      "set": "Phantasmal Flames",
      "qty": 5,
      "price": 100.47,
      "date": "2026-03-22",
      "notes": "Costco"
    },
    {
      "id": 1774149036221,
      "name": "Prismatic Tech Sticker (3pk)",
      "type": "Blister",
      "set": "Prismatic Evolutions",
      "qty": 3,
      "price": 25.01,
      "date": "2026-03-22",
      "notes": "Walmart"
    },
    {
      "id": 1774149036222,
      "name": "Journey Together Sticker (3pk)",
      "type": "Blister",
      "set": "Journey Together",
      "qty": 3,
      "price": 16.19,
      "date": "2026-03-22",
      "notes": "Walmart"
    },
    {
      "id": 1774149036223,
      "name": "Pokemon Day 2026 Collection",
      "type": "Box",
      "set": "",
      "qty": 12,
      "price": 17.75,
      "date": "2026-03-22",
      "notes": "XP, Target, Walmart"
    },
    {
      "id": 1774149036224,
      "name": "Journey Together Three Booster Blister Yanmega (2) Scrafty (2)",
      "type": "Blister",
      "set": "Journey Together",
      "qty": 4,
      "price": 15.51,
      "date": "2026-03-22",
      "notes": "Target"
    },
    {
      "id": 1774149036225,
      "name": "JT Booster Bundle",
      "type": "Booster",
      "set": "Journey Together",
      "qty": 5,
      "price": 32.61,
      "date": "2026-03-22",
      "notes": "WMT/PKC"
    },
    {
      "id": 1774149036226,
      "name": "DR Booster Bundle",
      "type": "Booster",
      "set": "Destined Rivals",
      "qty": 4,
      "price": 38.07,
      "date": "2026-03-22",
      "notes": "Walmart"
    },
    {
      "id": 1774149036227,
      "name": "Mega Zygarde ex Premium Collection",
      "type": "Box",
      "set": "",
      "qty": 3,
      "price": 45,
      "date": "2026-03-22",
      "notes": "PokeHive"
    },
    {
      "id": 1774149036228,
      "name": "Prismatic Sams (Special Box + Booster Bundle)",
      "type": "Box",
      "set": "Prismatic Evolutions",
      "qty": 2,
      "price": 52,
      "date": "2026-03-22",
      "notes": "Sam's"
    },
    {
      "id": 1774149036229,
      "name": "Mega/PFL 2 Pack Blister (Raikou) [3 Tab]",
      "type": "Blister",
      "set": "",
      "qty": 2,
      "price": 12.19,
      "date": "2026-03-22",
      "notes": "Target"
    },
    {
      "id": 1774149036230,
      "name": "Mega/PFL 2 Pack Blister (Raikou) [1 Tab]",
      "type": "Blister",
      "set": "",
      "qty": 15,
      "price": 14.24,
      "date": "2026-03-22",
      "notes": "Walgreens"
    },
    {
      "id": 1774149036231,
      "name": "Mega Charizard XY Tin",
      "type": "Tin",
      "set": "",
      "qty": 4,
      "price": 25.84,
      "date": "2026-03-22",
      "notes": "Target"
    },
    {
      "id": 1774149036232,
      "name": "ME01 Mega Evolutions 3 Pack Blister",
      "type": "Blister",
      "set": "Mega Evolutions",
      "qty": 4,
      "price": 16.41,
      "date": "2026-03-22",
      "notes": "5 Below"
    },
    {
      "id": 1774149036233,
      "name": "ME03 Ascended Heroes ETB",
      "type": "ETB",
      "set": "Ascended Heroes",
      "qty": 5,
      "price": 61.58,
      "date": "2026-03-22",
      "notes": "Target+Collector Cubby+Target"
    },
    {
      "id": 1774149036234,
      "name": "ME03 Ascended Heroes ETB",
      "type": "ETB",
      "set": "Ascended Heroes",
      "qty": 2.5,
      "price": 65.33,
      "date": "2026-03-22",
      "notes": "Wmt"
    },
    {
      "id": 1774149036235,
      "name": "ME03 Ascended Heroes Mini Tin",
      "type": "Tin",
      "set": "Ascended Heroes",
      "qty": 4,
      "price": 12.28,
      "date": "2026-03-22",
      "notes": ""
    },
    {
      "id": 1774149036236,
      "name": "ME03 Ascended Heroes Tech sticker (3pack)",
      "type": "Blister",
      "set": "Ascended Heroes",
      "qty": 1,
      "price": 21.75,
      "date": "2026-03-22",
      "notes": "Target"
    },
    {
      "id": 1774149036237,
      "name": "ME03 Ascended (Larry / Erika) (2pack)",
      "type": "Blister",
      "set": "Ascended Heroes",
      "qty": 4,
      "price": 12.5,
      "date": "2026-03-22",
      "notes": "Walgreens"
    },
    {
      "id": 1774149036238,
      "name": "Astral Radiance Sleeves",
      "type": "Sleeves",
      "set": "Astral Radiance",
      "qty": 5,
      "price": 6.51,
      "date": "2026-03-22",
      "notes": "Stop/Shop"
    },
    {
      "id": 1774149036239,
      "name": "Prismatic Tech Sticker (3pk)",
      "type": "Blister",
      "set": "Prismatic Evolutions",
      "qty": 2,
      "price": 22.78,
      "date": "2026-03-22",
      "notes": "Walmart (DK)"
    },
    {
      "id": 1774149036240,
      "name": "ME03 Ascended Heroes Tech sticker (3pack)",
      "type": "Blister",
      "set": "Ascended Heroes",
      "qty": 1,
      "price": 21.75,
      "date": "2026-03-22",
      "notes": "Target"
    },
    {
      "id": 1774149036241,
      "name": "ME03 Ascended (Larry / Erika) (2pack)",
      "type": "Blister",
      "set": "Ascended Heroes",
      "qty": 1,
      "price": 10.85,
      "date": "2026-03-22",
      "notes": "Target"
    },
    {
      "id": 1774149036242,
      "name": "ME03 Ascended Heroes ETB Case",
      "type": "ETB",
      "set": "Ascended Heroes",
      "qty": 1,
      "price": 1203,
      "date": "2026-03-22",
      "notes": "pfootball"
    },
    {
      "id": 1774149036243,
      "name": "Zard Tin",
      "type": "Tin",
      "set": "",
      "qty": 1,
      "price": 27.19,
      "date": "2026-03-22",
      "notes": "Walmart"
    },
    {
      "id": 1774149036244,
      "name": "Pokeball Tins",
      "type": "Tins",
      "set": "",
      "qty": 3,
      "price": 80,
      "date": "2026-03-22",
      "notes": ""
    },
    {
      "id": 1774149036245,
      "name": "Phantasmal Booster Bundle",
      "type": "Booster Bundle",
      "set": "Phantasmal Flames",
      "qty": 3,
      "price": 43.54,
      "date": "2026-03-22",
      "notes": "columbia"
    },
    {
      "id": 1774149036246,
      "name": "DR Tins",
      "type": "Tins",
      "set": "Destined Rivals",
      "qty": 3,
      "price": 36.29,
      "date": "2026-03-22",
      "notes": "columbia"
    },
    {
      "id": 1774227255766,
      "name": "ME01 Mega Evolutions ETB (Lucerio)",
      "type": "ETB",
      "set": "Mega Evolutions",
      "date": "2026-03-22",
      "qty": 2,
      "price": 54.99
    }
  ],
  "packs": [],
  "sales": []
}